odoo/addons/calendar_document_popup/README.rst
odoo/addons/calendar_document_popup/__init__.py
odoo/addons/calendar_document_popup/__manifest__.py
odoo/addons/calendar_document_popup/i18n/es.po
odoo/addons/calendar_document_popup/models/__init__.py
odoo/addons/calendar_document_popup/models/calendar_event.py
odoo/addons/calendar_document_popup/static/description/icon.png
odoo/addons/calendar_document_popup/views/calendar_views.xml
odoo_addon_calendar_document_popup-15.0.1.0.1.dist-info/METADATA
odoo_addon_calendar_document_popup-15.0.1.0.1.dist-info/WHEEL
odoo_addon_calendar_document_popup-15.0.1.0.1.dist-info/top_level.txt
odoo_addon_calendar_document_popup-15.0.1.0.1.dist-info/RECORD
